{"url": "https://www.thegatewaypundit.com/2024/06/caitlin-clark-snubbed-us-olympic-team-greatest-shooter", "uid": "thegatewaypundit.com-2024-06-caitlin-clark-snubbed-us-olympic-team-greatest-shooter", "images": ["https://www.thegatewaypundit.com/wp-content/uploads/2025/06/site-title-new-large2.png", "https://www.thegatewaypundit.com/wp-content/plugins/gtranslate/flags/svg/en-us.svg", "https://www.thegatewaypundit.com/wp-content/plugins/gtranslate/flags/svg/es.svg", "https://www.thegatewaypundit.com/wp-content/plugins/gtranslate/flags/svg/de.svg", "https://www.thegatewaypundit.com/wp-content/plugins/gtranslate/flags/svg/ja.svg", "https://www.thegatewaypundit.com/wp-content/uploads/2024/06/dc-stadium-caitlin-clark.jpg", "https://www.thegatewaypundit.com/wp-content/uploads/2024/06/women-bball.jpeg", "https://www.thegatewaypundit.com/wp-content/uploads/cropped-cropped-avatar-jim2-1-384x384.jpg", "https://www.thegatewaypundit.com/wp-content/uploads/2026/03/untitled-design-16-1200x630.png", "https://www.thegatewaypundit.com/wp-content/uploads/2026/01/protrumpnews-sidebar-newyears.jpg", "https://c.statcounter.com/9449268/0/3cc87ae0/0/"], "publication-date": "2024-06-08", "text": "CAITLIN CLARK FILLED ANOTHER STADIUM LAST NIGHT IN WASHINGTON DC!\n\nIt was the largest crowd to see a women’s professional basketball game in over 17 years!20,333 total tickets sold!\n\n\n\nAnd they got their money’s worth.Caitlin put on a clinic!\n\n30 points7 three-pointers8 rebounds6 assists4 steals\n\nCaitlin Clark WENT OFF in the Indiana Fever’s win over the Mystics\n\n30 PTS (53.3 FG%)7 3PM (53.8 3PT%)8 REB6 AST4 STL38 Minutes#WelcometotheW| Commissioner’s Cup presented by@coinbasepic.twitter.com/h2hfMR0P2O\n\n— WNBA (@WNBA)June 8, 2024\n\n\n\nCaitlin has sold out every venue she has played at this year.\n\nThis was an AWAY GAME!\n\nThis is the largest attendance of any WNBA game EVER! Caitlin Clark is the reason 20,333 total tickets soldpic.twitter.com/4SmDAKzGzc\n\n— Aura Sports (@AuraSportsHQ)June 8, 2024\n\n\n\nBut despite holding ALL of the major collegiate scoring records for women’s basketball EVER and leading the NCAA in assists in her last year – Caitlin Clark was omitted from the US Women’s Basketball Team it was announced today.\n\nCaitlin Clark wasinvitedto attend Team USA training camp in April, but was unable to attend due to her team’s trip to the NCAA Tournament final.\n\nHere isthe roster… Most of these names you HAVE NEVER heard of.\n\nHow many of these women are National Anthem kneelers who despise their country?\n\n\n\nCBS Sportsreported:\n\nIndiana Fever rookie Caitlin Clark is expected to be left off the Team USA women’s basketball roster for the upcoming Summer Olympics in Paris, David Eickholt of 247Sports confirms.\n\nUSA Today’s Christine Brennan first reported shortly after midnight Saturday.\n\nClark became the college basketball all-time leading scorer earlier this year, and she is currently putting up some impressive numbers in the WNBA.\n\nIn her first 14 games, she has averaged 16.8 points, 5.3 rebounds, 6.3 assists and 1.5 steals per game. She has also already put up two 30-point games — one of them being during the Fever’s 85-83 win over the Washington Mystics in which she reached a career-high seven 3-pointers. With that performance, Clark became the fastest rookie in WNBA history to record 200+ points and 50+ assists.\n\nNice job, idiots!\n\nWhat a HUGE mistake.\n\nWhen Caitlin Clark hit her third 3-pointer in four minutes in the third quarter, the crowd of over 20,000 immediately erupted in celebration.\n\nWith the noise, you would’ve thought it was a home game. But it wasn’t — it’s just what Clark draws.\n\nFrom D.C.:https://t.co/JPsAvWPgAk\n\n— Chloe Peterson (@chloepeterson67)June 8, 2024\n\n\n\nWhy leaving Caitlin Clark off the 2024 US Olympic women’s basketball team matters, a lot. I’ve reported on the team at every Olympics since 1984. I’ve watched the stunning lack of coverage & lack of interest every time. Here are four sections of my Feb column on this exact topic:pic.twitter.com/MjwqeVQdR8\n\n— Christine Brennan (@cbrennansports)June 8, 2024\n\n\n\nYou canemail Jim Hoft here, andread more of Jim Hoft's articles here.\n\n\n\nSign up now and stay ahead in the political landscape.\n\nVisitGatewayHispanic.comto read news of interest to the hispanic community.\n\nVisitAmericanGulag.orgto learn how to help the prisoners of the protest on January 6th.\n\nVisitTGPVideos.comto watch the latest exclusive videos from The Gateway Pundit.\n\nAs the mainstream media repeatedly fails and loses public trust, TGP has continued to offer accurate and timely reporting for almost two decades. VisitTGP FactCheckto see how we get it right.\n\nCheck outTGP FactCheckto see how terribly wrong the legacy media can get it.\n\n© 2026 The Gateway Pundit\n\nHome\n\nAbout us\n\nContact\n\nPrivacy\n\nTerms\n\nGet Ad Free", "title": "Caitlin Clark SNUBBED from US Olympic Team - THE GREATEST SHOOTER OF ALL TIME! - Like Leaving Michael Jordan Off Dream Team! - WTH? | The Gateway Pundit | by Jim Hoft", "top-image": "https://www.thegatewaypundit.com/wp-content/uploads/2025/06/site-title-new-large2.png", "domain": "www.thegatewaypundit.com", "lang": "en-US", "author": "Jim Hoft", "description": "", "keywords": ""}