{"url": "https://www.insideindianabusiness.com/articles/indiana-companies-help-fill-purify-pool-water-for-u-s-olympic-swim-trials", "uid": "insideindianabusiness.com-articles-indiana-companies-help-fill-purify-pool-water-for-u-s-olympic-swim-trials", "images": ["https://www.insideindianabusiness.com/wp-content/uploads/2022/04/iib-logo.png", "https://audio.ibj.com/sponsors/logos/iib/170347", "https://www.insideindianabusiness.com/wp-content/themes/iib/images/audio-player/rewind.svg", "https://www.insideindianabusiness.com/wp-content/themes/iib/images/audio-player/play.svg", "https://www.insideindianabusiness.com/wp-content/themes/iib/images/audio-player/pause.svg", "https://www.insideindianabusiness.com/wp-content/themes/iib/images/spinners/oval-dark.svg", "https://www.insideindianabusiness.com/wp-content/themes/iib/images/audio-player/fastforward.svg", "https://www.insideindianabusiness.com/wp-content/themes/iib/images/audio-player/volume.svg", "https://cdn.insideindianabusiness.com/wp-content/uploads/2024/06/Brad-Rhorer-Headshot-2024.jpg", "https://cdn.insideindianabusiness.com/wp-content/uploads/2021/09/iib-logo-white.svg", "https://px.ads.linkedin.com/collect/?pid=6160540&fmt=gif"], "publication-date": "2024-06-11", "text": "Two years ago, organizers reached out to ask the biggest question of all surrounding the U.S. Olympic Swim Trials in Indianapolis: could the city provide enough water to host the trials?\n\nThe answer was “yes,” and all of the water to fill two and a half Olympic pools comes from a single hydrant just outside Lucas Oil Stadium. Then, two Indiana companies take over to make sure it’s ready for showtime.\n\n“It’s definitely the most famous hydrant in the state right now,” said Paul Dicken, director of water distribution with Citizens Energy Group. “But it’s a typical fire hydrant.”\n\nDicken told Business of Health Reporter Kylie Veleta that Citizens has done similar projects, but not on the magnitude of the swim trials.\n\n“This is unique, obviously,” he said. “We hooked up some hoses to the hydrant, turn the hydrant on and connected to Spear Corp.’s piping that ran all the way into the Lucas Oil. We didn’t have to do a thing to the system, amazingly.”\n\nOnce all 2 million gallons of water were pumped into Lucas Oil, Spear Corp., a family-owned operation in Putnam County, took over. About 10 semi-truck loads delivered Spear’s massive piping and filtration system designed to pump the water to perfection.\n\n“We’re flowing about 3,000 gallons a minute for each pool through the system, and it’s UV treated as well,” said Brian Spear, president of Spear Corp. “So it goes through UV treatment before it goes back to the pool, and we chemically treat it.”\n\nThe water clarity is also key, not just for the swimmers but also for cameras getting underwater primetime TV shots. Spear said the water chemistry has to be balanced perfectly along with the correct temperature of around 79.5 degrees Fahrenheit.\n\nBrian Spear is no stranger to U.S. Olympic Swim Trials. His Hoosier company led the charge for three straight Olympic trials in Omaha, Nebraska.\n\n“Being in Indiana this time since we’re a local company, it’s just kind of a homecoming for us, too. We have always been in Omaha for the trials itself. And it’s cool to be involved with it there, but it’s a little extra special being here in Indianapolis.”\n\nThere’s a sense of pride for Citizens as well by helping set the nation’s biggest stage in swimming.\n\n“Even our front line guys that were down here helping with the planning stages, they all think it’s pretty neat stuff, too,” said Dicken. “So we’re just gracious that we’re able to be part of it.”\n\nAnd when the trials are over, citizens will be back in charge again. They’ll use hoses to drain the pool water, direct it into the storm drains and it will be back in Indiana’s wastewater.\n\nOne upcoming federal policy shift, known as Workforce Pell, has the potential to make lifelong learning more accessible...\n\nInside INdiana BusinessA division of IBJ Media\n\n1 Monument Circle, Suite 300Indianapolis, IN 46204\n\nPHONE: (317) 634-6200\n\nFAX: (317) 263-5060\n\nNEWSLETTER@IIBNEWS.COM\n\nCopyright © 2025 All Rights ReservedPrivacy Policy|Terms of Service\n\nBig business news.Teeny tiny price.$1/weekSubscribe Now\n\nBig business news.Teeny tiny price.$1/weekSubscribe Now\n\nBig business news.Teeny tiny price.$1/weekUpgrade Now\n\nBig business news.Teeny tiny price.$1/weekUpgrade Now\n\nTry us out for\n\n$1/week\n\nSubscribe Now\n\nAlready a paid subscriber?Log In\n\nTry us out for\n\n$1/week\n\nSubscribe Now\n\nAlready a paid subscriber?Log In\n\nTry us out for\n\n$1/week\n\nSubscribe Now\n\nAlready a paid subscriber?Log In\n\nTry us out for\n\n$1/week\n\nSubscribe Now\n\nAlready a paid subscriber?Log In", "title": "Indiana companies help fill, purify pool water for U.S. Olympic Swim Trials – Inside INdiana Business", "top-image": "https://www.insideindianabusiness.com/wp-content/uploads/2022/04/iib-logo.png", "domain": "www.insideindianabusiness.com", "lang": "en-US", "author": "", "description": "", "keywords": ""}