{"url": "https://www.straitstimes.com/sport/french-gloom-clouds-paris-olympics-six-months-from-start", "uid": "straitstimes.com-sport-french-gloom-clouds-paris-olympics-six-months-from-start", "images": ["https://cassette.sphdigital.com.sg/image/straitstimes/6237728ffc987e1e7ea0df092958ca86cc46b95992c2162712720f0d8e2f43e1"], "publication-date": "2024-01-22", "text": "Choose edition\n\nSearch\n\nsingapore\n\nasia\n\nworld\n\nopinion\n\nlife\n\nbusiness\n\nsport\n\nVisual\n\nPodcasts\n\nSPH Rewards\n\nSTClassifieds\n\nPaid press releases\n\nAdvertise with us\n\nFAQs\n\nContact us\n\nSign up now:Get the biggest sports news in your inbox\n\nParis 2024 organisers remain confident that sights such as beach volleyball in front of the Eiffel Tower.\n\nPHOTO: AFP\n\nPublishedJan 22, 2024, 05:46 PM\n\nUpdatedNov 08, 2024, 01:37 PM\n\nPARIS–Political bickering, ongoing grumbling about ticket prices and disruption to everyday life are souring the mood in the build-up to the Paris Olympics in July – something organisers blame on typical French pessimism.\n\nSeveral recent announcements have led to a spike in negative publicity for the sporting mega-event which will start in just six months and draw a television audience of billions.\n\nMany Parisians were dismayed in December by news that transport ticket prices are set to double for the duration of the event and that they should work from home to free up seats on busy metros and buses.\n\nThe unveiling of planned security measures led to claims some parts of the city would face Covid-19-style lockdowns, while controversy erupted about the environmental impact of a judges’ tower at the surfing venue in French Polynesia.\n\nOn top of it all, Paris’ Socialist Mayor Anne Hidalgo and President Emmanuel Macron’s centrist government fell out publicly after Hidalgo claimed that planned Paris transport upgrades would “not be ready”.\n\n“There have been a succession of issues that have been badly handled from a communication point of view,” said Philippe Moreau Chevrolet, a lecturer in communication at Sciences Po university in Paris and the founder of the MCBG Conseil public relations agency.\n\n“Instead of getting people behind the Games, they have created mistrust.”\n\nFrance’s association of hoteliers and restaurant owners issued an unusual statement earlier in January, condemning French politicians for their “anxiety-inducing” announcements around the Games and urging them to come together.\n\n“In general, we would strongly urge all of our public authorities, collectively and with solidarity, to speak positively and responsibly,” the statement added.\n\nOther recent complaints centre on the construction work that snares traffic daily around the capital, while resentment lingers over the handling of ticket sales in 2023 that saw many locals priced out.\n\nParis will see “the most expensive ticket prices in an athletics arena that we have witnessed at an Olympic Games”, said World Athletics president Sebastian Coe in December, adding he was worried the families of some athletes would be unable to attend.\n\nParis 2024 organisers remain confident that sights such as beach volleyball in front of the Eiffel Tower, swimming in the River Seine, or the marathon through the capital’s fabled streets will lift spirits once the flame is lit on July 26.\n\nThey make a distinction between the often noisy and attention-seeking media and political debate, and wider public opinion.\n\nA survey by the Odoxa group for RTL radio in November suggested that 65 per cent of French people were in favour of the Games – a fall of 11 points in two years but still a large majority with positive views.\n\nIn the Paris region, slightly more than half of people were in favour.\n\nOrganisers also point to the orderly preparations, as well as their budget restraint in comparison with other modern editions.\n\nMost of the sporting infrastructure is finished. The athletes’ village is almost ready to be furnished. Crucial metro and train line extensions will be ready in time, they insist.\n\n“What if everything went OK?” asked a headline in the left-wing Liberation newspaper at the start of 2024.\n\n“France is ready for the Olympics... but given the country’s gloomy mood and its unpopular leaders, there is no sign of popular fervour,” it added.\n\nTony Estanguet, the head of the Paris 2024 organising committee, has criticised “Olympics bashing” in the media and despaired of his compatriots’ tendency to look on the downside.\n\n“We like to look at what is not going well, focus on things that are out of place, concentrate on our weak spots, whereas some countries like to play up their qualities and strengths,” he told France Inter radio in January.AFP\n\nOlympics 2024\n\nOlympics\n\nFrance\n\nE-paper\n\nNewsletters\n\nPodcasts\n\nRSS Feed\n\nAbout Us\n\nTerms & Conditions\n\nPersonal Data Protection Notice\n\nNeed help? Reach us here.\n\nAdvertise with us\n\n\n\n", "title": "French gloom clouds Paris Olympics, six months from start | The Straits Times", "top-image": "https://cassette.sphdigital.com.sg/image/straitstimes/6237728ffc987e1e7ea0df092958ca86cc46b95992c2162712720f0d8e2f43e1", "domain": "www.straitstimes.com", "lang": "en", "author": "", "description": "Political bickering, ongoing grumbling about ticket prices and disruption to everyday life are souring the mood. Read more at straitstimes.com.", "keywords": ""}