{"url": "https://www.techradar.com/pro/security/microsoft-reveals-major-russian-cyber-threats-that-looked-to-target-paris-olympics", "uid": "techradar.com-pro-security-microsoft-reveals-major-russian-cyber-threats-that-looked-to-target-paris-olympics", "images": ["https://sb.scorecardresearch.com/p/?c1=2&c2=10055482&cv=4.4.0&cj=1", "https://vanilla.futurecdn.net/techradar/media/shared/img/flags/nosize/US.svg", "https://www.techradar.com/media/shared/img/flags/nosize/SG.svg", "https://www.techradar.com/media/shared/img/flags/nosize/DK.svg", "https://www.techradar.com/media/shared/img/flags/nosize/FI.svg", "https://www.techradar.com/media/shared/img/flags/nosize/NO.svg", "https://www.techradar.com/media/shared/img/flags/nosize/SE.svg", "https://www.techradar.com/media/shared/img/flags/nosize/GB.svg", "https://www.techradar.com/media/shared/img/flags/nosize/IT.svg", "https://www.techradar.com/media/shared/img/flags/nosize/NL.svg", "https://www.techradar.com/media/shared/img/flags/nosize/BE.svg", "https://www.techradar.com/media/shared/img/flags/nosize/FR.svg", "https://www.techradar.com/media/shared/img/flags/nosize/DE.svg", "https://www.techradar.com/media/shared/img/flags/nosize/ES.svg", "https://www.techradar.com/media/shared/img/flags/nosize/US.svg", "https://www.techradar.com/media/shared/img/flags/nosize/CA.svg", "https://www.techradar.com/media/shared/img/flags/nosize/MX.svg", "https://www.techradar.com/media/shared/img/flags/nosize/AU.svg", "https://www.techradar.com/media/shared/img/flags/nosize/NZ.svg", "https://cdn.mos.cms.futurecdn.net/kHR7hTFieuBmjcpgHnKHh4.jpg", "https://cdn.mos.cms.futurecdn.net/KATu6scqjuj5bCqHLRubXn.jpg", "https://cdn.mos.cms.futurecdn.net/8E5VDX9TsMih9AjiZnLmiB.jpg", "https://cdn.mos.cms.futurecdn.net/8UGPuf8G5qYJTmRHnqW9DH.jpg", "https://cdn.mos.cms.futurecdn.net/SmS7JrH5vq6kYg7Dea9UT6.jpg", "https://cdn.mos.cms.futurecdn.net/4PtWAkhYfQ2pQANczURRVf.jpg", "https://cdn.mos.cms.futurecdn.net/UNBhCvCBZ47GpjzV7AN5mG.jpg", "https://cdn.mos.cms.futurecdn.net/VpDU3zwnzbGKAaKDHPjVa5.jpg", "https://cdn.mos.cms.futurecdn.net/TWkP7ZurZMY6uepDxsK6Ha.jpg", "https://cdn.mos.cms.futurecdn.net/Ri2dNNTvgmKGsMuhNDCavZ.jpg", "https://cdn.mos.cms.futurecdn.net/ThNyuwnA55tfcixfqWcEcA.jpg", "https://cdn.mos.cms.futurecdn.net/cU4E2awxkdftorLjkbFyqm.jpeg", "https://cdn.mos.cms.futurecdn.net/JhaUWMoSPUkXvYwQgATgp4.jpg", "https://cdn.mos.cms.futurecdn.net/EEXAxCUDKAq3frELz3rVYY.jpg", "https://cdn.mos.cms.futurecdn.net/MXqmsVRQzx9hefCvT8TupP.jpg", "https://cdn.mos.cms.futurecdn.net/RzQzcXdVXVPSTnLaeRTzRT.jpg", "https://cdn.mos.cms.futurecdn.net/UJ5CFPQLDaMmXUqcw3CEXh-840-80.jpg", "https://cdn.mos.cms.futurecdn.net/Ffiqx9qBt9gGY6VJ6zCMhZ-840-80.png", "https://cdn.mos.cms.futurecdn.net/t2hoLECgtFw55mgfLEdBUU-840-80.jpg", "https://cdn.mos.cms.futurecdn.net/UJ5CFPQLDaMmXUqcw3CEXh.jpg", "https://cdn.mos.cms.futurecdn.net/Ffiqx9qBt9gGY6VJ6zCMhZ.png", "https://cdn.mos.cms.futurecdn.net/t2hoLECgtFw55mgfLEdBUU.jpg", "https://cdn.mos.cms.futurecdn.net/n2u3qWhkEbqXRzD4MJnbgU.jpg", "https://cdn.mos.cms.futurecdn.net/eVgzzXmQMEyvzfYvAaAMrX.jpg", "https://cdn.mos.cms.futurecdn.net/XRZnyNZVHb27CjWT9rGzg7.jpg", "https://cdn.mos.cms.futurecdn.net/YGL8hBkUUMwCEwbuXtAQeA.jpg", "https://cdn.mos.cms.futurecdn.net/co3X3Vbz8avMLRgvKTSfgC.jpg", "https://cdn.mos.cms.futurecdn.net/MPfrfBiAx7wKAix6yiWWUC.jpg", "https://cdn.mos.cms.futurecdn.net/GJ8T4oA8G7TYJwTEhkwJAF.jpg", "https://cdn.mos.cms.futurecdn.net/96gxyDA4DGGmJyyHJ2fqvC.jpg", "https://cdn.mos.cms.futurecdn.net/v8LYyvBfpYanyKNXKLA8RF.jpg", "https://cdn.mos.cms.futurecdn.net/XZD7n3sgjSviQ9G3cjyf8C.jpg", "https://cdn.mos.cms.futurecdn.net/YQaVTQE6JAfu6bvPgwmd5U.jpg", "https://cdn.mos.cms.futurecdn.net/YuCcpzjfQr4yZbCajCQdR4.jpg", "https://cdn.mos.cms.futurecdn.net/kmnJt2kZgDb95qYZEfVnfT.jpg", "https://cdn.mos.cms.futurecdn.net/flexiimages/mednnv697g1760357120.png"], "publication-date": "2024-06-04", "text": "Major Russian misinformation campaign has Paris Olympics in its sights\n\nWhen you purchase through links on our site, we may earn an affiliate commission.Here’s how it works.\n\nMultiple Russian state-sponsored threat actors are actively running misinformation campaigns regarding theSummer Olympic Gamesthat are due in Paris, France, this summer. The goal of the campaigns, apparently, is to make people afraid and have them avoid the event altogether.\n\nTheMicrosoftThreat Analysis Center (MTAC) recently published anew reportoutlining at least two separate threat actor groups, Storm-1679, and Storm-1099, working at the same time, and for the same goal.\n\nReaders might remember the latter from previous reports, when Storm-1099 was attributed with a misinformation campaign that Ukraine was selling donated weapons to Hamas to commit atrocities in Israel.\n\nFor these campaigns, the groups are doing a number of things, including spoofing popular news outlets in France and elsewhere in Europe, as well asimpersonatingactors and celebrities.\n\nIn fact, Microsoft says the misinformation masters created a fake Netflix documentary called “Olympics Has Fallen”, sporting the streaming service’s logo and narrated by an AI-generated Tom Cruise voice.\n\n“Further analysis confirmed the fake documentary used AI-generated audio resembling Cruise's voice to imply his participation, spoofed Netflix's iconic intro scene and corporate branding, and promoted bogus five-star reviews from reputable media outlets like the New York Times, the Washington Post, and the BBC, all amid slick computer-generated special effects,\" the report noted.\n\nRussian state-sponsored hackers have a history of meddling in both national and global events, with the goal of disrupting and spreading misinformation. The US presidential elections, 2018 Winter Olympic Games in South Korea, French President Macron’s presidential campaign, those are just some of the events that Microsoft claims Russia’s hackers interfered with.\n\nSign up to the TechRadar Pro newsletter to get all the top news, opinion, features and guidance your business needs to succeed!\n\nSead is a seasoned freelance journalist based in Sarajevo, Bosnia and Herzegovina. He writes about IT (cloud, IoT, 5G, VPN) and cybersecurity (ransomware, data breaches, laws and regulations). In his career, spanning more than a decade, he’s written for numerous media outlets, including Al Jazeera Balkans. He’s also held several modules on content writing for Represent Communications.\n\nTechRadar is part of Future US Inc, an international media group and leading digital publisher.Visit our corporate site.\n\n©\nFuture US, Inc. Full 7th Floor, 130 West 42nd Street,\nNew York,\nNY 10036.\n\nPlease login or signup to comment\n\nPlease wait...", "title": "Microsoft reveals major Russian cyber threats that looked to target Paris Olympics | TechRadar", "top-image": "https://sb.scorecardresearch.com/p/?c1=2&c2=10055482&cv=4.4.0&cj=1", "domain": "www.techradar.com", "lang": "en", "author": "", "description": "Major Russian misinformation campaign has Paris Olympics in its sights", "keywords": ""}