{"url": "https://www.kob.com/new-mexico/olympic-skateboarder-coming-home-for-event-in-albuquerque/", "uid": "kob.com-new-mexico-olympic-skateboarder-coming-home-for-event-in-albuquerque", "images": [], "publication-date": "2024-04-26", "text": "ALBUQUERQUE, N.M. — An Albuquerque native and Olympic skateboarder will appear at a skate and food truck event Saturday in the South Valley.\n\nMariah Duran will appear at the South Valley Skate and Food Truck Fest, April 27. It’s happening at the Rio Bravo Skate Park from 11 a.m. to 2 p.m., and is open to the public.\n\nU.S. Eagle Federal Credit Union will host Duran. She will hold a skateboard clinic, teach tips and tricks to skateboarders, showcase skateboarding styles and meet with the community and sign autographs.\n\nGuests are encouraged to bring nonperishable food items to support the Rio Grande Food Project, the largest food pantry on Albuquerque’s West Side. The event will also feature prizes and food trucks for attendees.\n\nDuran will compete in the Paris Olympics as a part of the USA Skateboarding Team. Already she has won gold in the X Games and competed in the inaugural USA Skateboarding Team during the 2020 Tokyo Games.\n\nAny person with disabilities who needs help accessing the content of the FCC Public File may contact KOB via ouronline formor call 505-243-4411.\n\nThis website is not intended for users located within the European Economic Area.©KOB-TV, LLCA Hubbard Broadcasting Company\n\nKOB Follow", "title": "Olympic skateboarder coming home for event this Saturday - KOB.com", "top-image": "", "domain": "www.kob.com", "lang": "en-US", "author": "Jonathan Fjeld", "description": "An Albuquerque native and Olympic skateboarder will appear at a skate and food truck event Saturday in the South Valley.", "keywords": ""}