{"url": "https://eastasiaforum.org/2024/08/10/will-chinas-doping-controversy-sink-the-olympics/", "uid": "eastasiaforum.org-2024-08-10-will-chinas-doping-controversy-sink-the-olympics", "images": ["https://eastasiaforum.org/wp-content/themes/carbonate/assets/dist/img/header__logo.svg", "https://eastasiaforum.org/wp-content/uploads/2024/08/2024-06-07T205728Z_1017063639_UP1EK671M7QWQ_RTRMADP_3_OLYMPICS-2024-RINGS-EIFFEL-TOWER-scaled-1024x682-c-default.webp", "https://eastasiaforum.org/wp-content/uploads/2024/08/adam-masters-225x300.jpg"], "publication-date": "2024-08-10", "text": "Peer reviewed analysis from world leading experts\n\nAustralian National University\n\n\n\nThe dispute between the United States and the World Anti-Doping Agency over positive doping tests by Chinese athletes rages on with a US congressional committee invoking the Rodchenkov Anti-Doping Act 2019 to prompt an investigation. The decision to launch its own investigation demonstrates that the United States is not only willing to create an extraterritorial enforcement regime against sport corruption, but also has the political will to exercise such powers. The power struggle between the United States, China and the International Olympic Committee threatens to undermine the success of future Olympic Games.\n\n‘Faster, Higher, Stronger – Together’ is the Olympic motto and it is likely that all but the last of these elements will apply to the fast-moving dispute between the United States and the World Anti-Doping Agency (WADA) over positive tests by Chinese athletes. While there will be intensive coverage as the Paris Olympics unfold, the longer-term impacts also need consideration.\n\nIn late 2020 and early 2021, 23 Chinese swimmers tested positive for trace amounts of trimetazidine — a banned substance. The investigation by the China Anti-Doping Agency concluded the substance had been accidently ingested via environmental contamination in a hotel kitchen. The athletes were allowed to compete in the2021 Tokyo Olympics. The China Anti-Doping Agency investigation was audited byWorld Aquaticsand thenreviewed by WADAwho determined that ‘according to all the available evidence — scientific and otherwise — this was not a case of doping but rather one of no-fault, environmental contamination’.\n\nIn May 2024, a US congressional committeecalled on the US Department of Justice and International Olympic Committee (IOC)to inquire into WADA’s decision to allow the athletes to compete in Tokyo, invoking the Rodchenkov Anti-Doping Act of 2019 (RADA) to motivate the Department of Justice. The congressional committee has heardevidencefrom US athletes and the United States Anti-Doping Agency (USADA).\n\nWhile WADA were invited to have a representative appear before the committee,it declined. WADA’s Director General said WADA would not heed the calls for the 23 athlete case files to be released to the US government because they were confidential and it would respond in kind to Chinese authorities if they request US athlete case files. According to a report byThe New York Timeson 4 July, the US Department of Justice investigation has commenced.\n\nDuring the Paris 2024 Olympics, different elements of this scandal will continue to play out. The opportunity for political point scoring — both domestic and abroad — will be irresistible to leaders in both countries. But the devil is in the details ofRADAand the extraterritorial powers the United States has granted itself to criminalise doping conspiracies in elite sporting competitions across the world.\n\nThe RADA legislation was drafted in the wake of therevelations made by whistleblower Dr Grigory Rodchenkovthat the Russian government had systematically corrupted anti-doping processes andWADA’s failure to suspendthe Russian Anti-Doping Agency for missing an imposed deadline in 2018. In 2015, the United States had exercised its extraterritorial powers by having 14 FIFA officials arrested in Switzerland overbribery allegationsrelated to broadcast rights.\n\nThe current investigation demonstrates that the United States is not only willing to create an extraterritorial enforcement regime against sport corruption, but also has the political will to exercise such powers. A key limitation to RADA is the requirement for dual criminality to be met underextradition treaties— that is an offence must be punishable under the laws of both of the treaty states.\n\nWhile RADA criminalises doping conspiracies in the United States, this is relatively new national law and not a common offence globally. Without dual criminality, most officials and organisations like WADA or national sporting organisations tainted by doping scandals can safely ignore this reality — for now.\n\nThe next Summer Olympics will be the 2028 Los Angeles games and the IOC has just announcedSalt Lake Cityas the hosts for the 2034 Winter Olympics. Any official of an organisation suspected by the United States of breaching RADA will likely find themselves under the jurisdiction of RADA.\n\nThe Salt Lake City Winter Olympics contract comes with a clause to protect WADA. Language has been added,according to John Coates, Chair of the IOC Legal Affairs Commission to ‘protect the integrity of the international anti-doping system’.\n\nNudging local, state or federal lawmakers is not unusual for the IOC. The IOC providesmodel criminal law against match-fixingand adherence to the WADA code and anti-doping measures are a requirement for host nations as well as individual sports. Even Olympic-relatedintellectual propertyrequires legislative safeguards.\n\nWhat we have in effect is a clash between three powerful actors — two nation states and the Olympic movement. Each is concerned with their prestige. China cannot acknowledge the possibility of systemic doping as was uncovered in the Russian case, while the United Statesrefuses to acknowledgethe possibility of environmental contamination though WADA agreed environmental contamination was reasonable for the positive tests.\n\nThe IOC has much to lose if the two most powerful nations in the world cannot compete amicably on the sporting field.\n\nIt is difficult to avoid conflating the position of nations given international sport is an exercise insoft power. While the US Congress is acting, other nations and their anti-doping agencies will take different positions, with many remaining neutral. The strong sporting nations — rich countries who can invest in recreational activities — will have a voice. This said, such conflicts are principally the politics of sport, rather than that of nations. A repeat of the 1980 and 1984 Cold War era boycotts of the Moscow and Los Angeles Olympic Games would be far more damaging today given the rise of Asia in global sports.\n\nAdam Masters is Executive Director of the Transnational Research Institute on Corruption at The Australian National University.\n\nEAF|China|Will China’s doping controversy sink the Olympics?\n\nThe US is hypocrital. Its allegations are without real evidence and just exploiting the uncertainties. Meanwhile USADA knew about athletes doping but yet let them off the hook and let them compete without punishment or informing Wada in exchange for ratting in others. This ruins trust in the system. They should clean their own house first before lecturing others otherwise it’s nothing more than geopolitics rather than showing integrity themselves.\n\nChinese had 23 swimmers who had tested positive before the Tokyo olympic games, so China has nothing to complain about. They should never have been allowed to compete in the olympics again. Once you’re caught there should be no second chance. This goes for US or any other swimmers who are caught and no flaky ‘contaminated meat’ excuses should be entertained\n\nSign up to receive free daily think pieces from leading analysts or our weekly digest, that includes our editorial and a collection of recent articles in brief.\n\n\n\n\n\nArticle printed fromEast Asia Forum (https://www.eastasiaforum.org)\n\nCopyright ©2025 East Asia Forum. All rights reserved.\n\nDid you know you can receive East Asia Forum analysis directly to your inbox?\n\nJoin our mailing list to never miss an update from top Asia analysts.\n\nSubscribe", "title": "Will China’s doping controversy sink the Olympics? | East Asia Forum", "top-image": "https://eastasiaforum.org/wp-content/themes/carbonate/assets/dist/img/header__logo.svg", "domain": "eastasiaforum.org", "lang": "en", "author": "Adam Masters", "description": "The US investigation into the decision to allow Chinese swimmers to compete in the 2021 Tokyo Olympic Games despite testing positive for a banned substance has put the future of the Olympic Games in deep water.", "keywords": ""}